rehearser/__init__.py
rehearser/constants.py
rehearser/mock_generator.py
rehearser/rehearser.py
rehearser/rehearser_interactions_file_mixin.py
rehearser/rehearser_method.py
rehearser/rehearser_proxy.py
rehearser/utils.py
rehearser-0.1.19.dist-info/LICENSE
rehearser-0.1.19.dist-info/METADATA
rehearser-0.1.19.dist-info/WHEEL
rehearser-0.1.19.dist-info/top_level.txt
rehearser-0.1.19.dist-info/RECORD
